{
  "version": "0.3.3-13-gb8e301b",
  "description": "CLI for StreamX - preview version",
  "homepage": "https://www.streamx.dev",
  "license": "EULA",
  "url": "https://github.com/streamx-dev/streamx-cli-preview/releases/download/0.3.3-13-gb8e301b/streamx-0.3.3-13-gb8e301b.zip",
  "hash": "sha256:9ff2b2ef367a1017eea7f25a6e5f3e483a1e32b1cba65a96bb95b8ecf2940d1b",
  "extract_dir": "streamx-0.3.3-13-gb8e301b",
  "env_add_path": "bin",
  "suggest": {
    "JDK": [
      "java/oraclejdk",
      "java/openjdk"
    ]
  },
  "checkver": {
    "url": "https://github.com/streamx-dev/streamx-cli-preview/releases/latest",
    "re": "v([\\d.]+).zip"
  },
  "autoupdate": {
    "url": "https://github.com/streamx-dev/streamx-cli-preview/releases/download/$version/streamx-$version.zip",
    "extract_dir": "streamx-$version",
    "hash": {
      "url": "$url.sha256"
    }
  }
}
